airflow/providers/microsoft/mssql/__init__.py
airflow/providers/microsoft/mssql/get_provider_info.py
airflow/providers/microsoft/mssql/dialects/__init__.py
airflow/providers/microsoft/mssql/dialects/mssql.py
airflow/providers/microsoft/mssql/hooks/__init__.py
airflow/providers/microsoft/mssql/hooks/mssql.py
apache_airflow_providers_microsoft_mssql-4.4.1.dist-info/entry_points.txt
apache_airflow_providers_microsoft_mssql-4.4.1.dist-info/licenses/LICENSE
apache_airflow_providers_microsoft_mssql-4.4.1.dist-info/licenses/NOTICE
apache_airflow_providers_microsoft_mssql-4.4.1.dist-info/WHEEL
apache_airflow_providers_microsoft_mssql-4.4.1.dist-info/METADATA
apache_airflow_providers_microsoft_mssql-4.4.1.dist-info/RECORD
